inka_clean/__init__.py
inka_clean/__main__.py
inka_clean/heading_adjuster.py
inka_clean/parser.py
inka_clean-0.1.2.dist-info/METADATA
inka_clean-0.1.2.dist-info/WHEEL
inka_clean-0.1.2.dist-info/entry_points.txt
inka_clean-0.1.2.dist-info/top_level.txt
inka_clean-0.1.2.dist-info/RECORD
