Metadata-Version: 2.4
Name: inka-clean
Version: 0.1.2
Summary: Remove inka2 metadata from markdown files while preserving content
Author-email: sysid <sysid@gmx.de>
Requires-Python: >=3.12
